cryptemis/__init__.py
cryptemis/cryptemis.py
cryptemis-0.0.1.data/scripts/cryptemis
cryptemis-0.0.1.dist-info/LICENSE
cryptemis-0.0.1.dist-info/METADATA
cryptemis-0.0.1.dist-info/WHEEL
cryptemis-0.0.1.dist-info/top_level.txt
cryptemis-0.0.1.dist-info/RECORD
